pysshm/__init__.py
pysshm/cli.py
pysshm/exception.py
pysshm/log.py
pysshm/ssm.py
pysshm-0.3.3.dist-info/entry_points.txt
pysshm-0.3.3.dist-info/WHEEL
pysshm-0.3.3.dist-info/METADATA
pysshm-0.3.3.dist-info/RECORD
